[
  {
    "ID": 0,
    "Question": "BASE",
    "Response": [
      "A",
      "B"
    ],
    "Voters": [],
    "VoteCodes": [],
    "Admin": "",
    "Authorized": [],
    "Ballots": [],
    "Result": {}
  },
  {
    "ID": "0f760d18-3ffa-450b-8b3d-8513b4346353",
    "Question": "Qui est le meilleur?",
    "Response": [
      "Valentin",
      "Oscar"
    ],
    "Voters": [
      "44f310b7-36e4-4521-aad8-40eef4c57954"
    ],
    "VoteCodes": [
      61
    ],
    "Admin": "44f310b7-36e4-4521-aad8-40eef4c57954",
    "Authorized": [],
    "Ballots": [],
    "Result": {}
  }
]